barcodes/__init__.py
barcodes/bcode_logic.py
barcodes/gui.py
barcodes/main.py
barcodes/tools/__init__.py
barcodes/tools/icons.py
meerk40t_barcodes-0.2.7.dist-info/LICENSE
meerk40t_barcodes-0.2.7.dist-info/METADATA
meerk40t_barcodes-0.2.7.dist-info/WHEEL
meerk40t_barcodes-0.2.7.dist-info/entry_points.txt
meerk40t_barcodes-0.2.7.dist-info/top_level.txt
meerk40t_barcodes-0.2.7.dist-info/zip-safe
meerk40t_barcodes-0.2.7.dist-info/RECORD
