Metadata-Version: 2.1
Name: meerk40t-barcodes
Version: 0.2.7
Summary: MeerK40t Barcode Extension
Home-page: https://github.com/meerk40t/meerk40t-barcodes
Author: jpirnay
Author-email: tatarize@gmail.com
License: MIT
Keywords: lasercutter,laser,vector,parser
Classifier: Development Status :: 5 - Production/Stable
Classifier: License :: OSI Approved :: MIT License
Classifier: Operating System :: OS Independent
Classifier: Programming Language :: Python
Classifier: Programming Language :: Python :: 3.6
Classifier: Programming Language :: Python :: 3.7
Classifier: Programming Language :: Python :: 3.8
Classifier: Programming Language :: Python :: 3.9
Classifier: Topic :: Multimedia :: Graphics
Classifier: Topic :: Multimedia :: Graphics :: Editors :: Vector-Based
Classifier: Topic :: Utilities
License-File: LICENSE
Requires-Dist: meerk40t >=0.8.0001
Requires-Dist: qrcode >=7.0
Requires-Dist: python-barcode >=0.10
